Metadata-Version: 1.0
Name: princeton-bibreduce
Version: 0.2
Summary: Reduce authors/titles/links in .bib files
Home-page: UNKNOWN
Author: Alex Tait
Author-email: atait@princeton.edu
License: MIT
Platform: UNKNOWN
